{"results":[{"title":"Lightened Up Easy Slow Cooker Beef and Mushrooms","id":"Lightened-Up-Easy-Slow-Cooker-Beef-and-Mushrooms","sourceName":"Simple Nourished Living","image":"images/recipes/Lightened-Up-Easy-Slow-Cooker-Beef-and-Mushrooms.jpeg","tags":["Ketogenic","Lunch","Main Course","Main Dish","Dinner","Dairy Free"],"readyInMinutes":15,"likes":569},{"title":"30-minute chicken, mushrooms and peas dinner","id":"30-minute-chicken-mushrooms-and-peas-dinner","sourceName":"Casaveneracion","image":"images/recipes/30-minute-chicken-mushrooms-and-peas-dinner.jpg","tags":["Ketogenic","Lunch","Main Course","Main Dish","Dinner","Gluten Free"],"readyInMinutes":35,"likes":100},{"title":"Taco Potatoes","id":"Taco-Potatoes","sourceName":"Recipes Food and Cooking","image":"images/recipes/Taco-Potatoes.jpg","tags":["Ketogenic","Lunch","Main Course","Main Dish","Dinner","Gluten Free","Mexican"],"readyInMinutes":75,"likes":22}],"name":"cream of mushroom soup","page":0,"total":1}
