{"results":[{"title":"15-Minute Miso Soup with Greens and Tofu","id":"15-Minute-Miso-Soup-with-Greens-and-Tofu","sourceName":"Minimalist Baker","image":"images/recipes/15-Minute-Miso-Soup-with-Greens-and-Tofu.jpg","tags":["Vegetarian","Soup","Gluten Free","Dairy Free","Lacto Ovo Vegetarian","Vegan","Japanese","Asian","Fall","Winter"],"readyInMinutes":15,"likes":2831},{"title":"Sunny Raw Nori Rolls","id":"Sunny-Raw-Nori-Rolls","sourceName":"Vegetarian Times","image":"images/recipes/Sunny-Raw-Nori-Rolls.jpg","tags":["Vegetarian","Side Dish","Gluten Free","Dairy Free","Lacto Ovo Vegetarian","Vegan"],"readyInMinutes":45,"likes":420}],"name":"nori","page":0,"total":1}
