{"results":[{"title":"Green Chile Bacon Cheeseburger Dip","id":"Green-Chile-Bacon-Cheeseburger-Dip","sourceName":"Boulder Locavore","image":"images/recipes/Green-Chile-Bacon-Cheeseburger-Dip.jpg","tags":["Ketogenic","Condiment","Dip","Spread","Gluten Free","Primal","American","Super Bowl"],"readyInMinutes":30,"likes":477},{"title":"Shrimp Poached in Coconut Milk with Fresh Herbs (Yerra Moolee)","id":"Shrimp-Poached-in-Coconut-Milk-with-Fresh-Herbs-(Yerra-Moolee)","sourceName":"Epicurious","image":"images/recipes/Shrimp-Poached-in-Coconut-Milk-with-Fresh-Herbs-(Yerra-Moolee).jpg","tags":["Ketogenic","Lunch","Main Course","Main Dish","Dinner","Gluten Free","Dairy Free","Pescatarian"],"readyInMinutes":45,"likes":313},{"title":"Santa Fe Strip Steaks","id":"Santa-Fe-Strip-Steaks","sourceName":"Taste of Home","image":"images/recipes/Santa-Fe-Strip-Steaks.jpg","tags":["Ketogenic","Lunch","Main Course","Main Dish","Dinner","Gluten Free","Valentine's Day","Father's Day"],"readyInMinutes":25,"likes":50}],"name":"green chilies","page":0,"total":1}
