{"results":[{"title":"Maggie’s Quinoa & Adzuki Bean Veggie Burgers","id":"Maggie's-Quinoa-and-Adzuki-Bean-Veggie-Burgers","sourceName":"Simply Sugar and Gluten Free","image":"images/recipes/Maggie's-Quinoa-and-Adzuki-Bean-Veggie-Burgers.jpg","tags":["Vegetarian","Side Dish","Gluten Free","Dairy Free","Lacto Ovo Vegetarian","Vegan","American"],"readyInMinutes":70,"likes":1171},{"title":"Mustard Salmon Sheet-Pan Dinner","id":"Mustard-Salmon-Sheet-Pan-Dinner","sourceName":"Foodie Crush","image":"images/recipes/Mustard-Salmon-Sheet-Pan-Dinner.jpg","tags":["Pescetarian","Lunch","Main Course","Main Dish","Dinner","Gluten Free","Dairy Free","Pescatarian"],"readyInMinutes":30,"likes":396},{"title":"Easy Lamb Vindaloo","id":"Easy-Lamb-Vindaloo","sourceName":"Three Many Cooks","image":"images/recipes/Easy-Lamb-Vindaloo.jpg","tags":["Ketogenic","Lunch","Main Course","Main Dish","Dinner","Gluten Free","Dairy Free","Indian","Asian"],"readyInMinutes":45,"likes":35},{"title":"Pork or Lamb Vindaloo","id":"Pork-or-Lamb-Vindaloo","sourceName":"Epicurious","image":"images/recipes/Pork-or-Lamb-Vindaloo.jpg","tags":["Ketogenic","Lunch","Main Course","Main Dish","Dinner","Gluten Free","Dairy Free","Indian","Asian"],"readyInMinutes":45,"likes":34},{"title":"Horseradish-Crusted Whitefish with Rémoulade","id":"Horseradish-Crusted-Whitefish-with-Remoulade","sourceName":"Epicurious","image":"images/recipes/Horseradish-Crusted-Whitefish-with-Remoulade.png","tags":["Ketogenic","Lunch","Main Course","Main Dish","Dinner","Dairy Free","Pescatarian"],"readyInMinutes":45,"likes":2}],"name":"grainy mustard","page":0,"total":1}
