{"results":[{"title":"Baked Sriracha Butternut Squash Fries","id":"Baked-Sriracha-Butternut-Squash-Fries","sourceName":"Oh My Veggies","image":"images/recipes/Baked-Sriracha-Butternut-Squash-Fries.jpg","tags":["Vegetarian","Side Dish","Gluten Free","Dairy Free","Lacto Ovo Vegetarian","Fodmap Friendly","Vegan","American"],"readyInMinutes":55,"likes":8695},{"title":"Warm Roasted Butternut Squash and Quinoa Salad","id":"Warm-Roasted-Butternut-Squash-and-Quinoa-Salad","sourceName":"The Kitchen McCabe","image":"images/recipes/Warm-Roasted-Butternut-Squash-and-Quinoa-Salad.jpg","tags":["Vegetarian","Lunch","Main Course","Main Dish","Dinner","Dairy Free","Lacto Ovo Vegetarian"],"readyInMinutes":45,"likes":7632},{"title":"Oven Roasted Vegetables","id":"Oven-Roasted-Vegetables","sourceName":"A Spicy Perspective","image":"images/recipes/Oven-Roasted-Vegetables.jpg","tags":["Vegetarian","Side Dish","Gluten Free","Dairy Free","Paleolithic","Lacto Ovo Vegetarian","Primal","Vegan"],"readyInMinutes":55,"likes":7245},{"title":"Butternut Squash & Chickpea Coconut Curry (Crock Pot )","id":"Butternut-Squash-and-Chickpea-Coconut-Curry-(Crock-Pot-)","sourceName":"Tasty Yummies","image":"images/recipes/Butternut-Squash-and-Chickpea-Coconut-Curry-(Crock-Pot-).jpg","tags":["Vegetarian","Side Dish","Gluten Free","Dairy Free","Lacto Ovo Vegetarian","Vegan","Indian","Asian"],"readyInMinutes":30,"likes":6244},{"title":"Orzo with Butternut Squash, Spinach & Blue Cheese","id":"Orzo-with-Butternut-Squash-Spinach-and-Blue-Cheese","sourceName":"The Kitchn","image":"images/recipes/Orzo-with-Butternut-Squash-Spinach-and-Blue-Cheese.jpg","tags":["Vegetarian","Side Dish","Lacto Ovo Vegetarian"],"readyInMinutes":45,"likes":6071},{"title":"Roasted Butternut Squash Hummus","id":"Roasted-Butternut-Squash-Hummus","sourceName":"The Healthy Maven","image":"images/recipes/Roasted-Butternut-Squash-Hummus.jpg","tags":["Vegetarian","Side Dish","Gluten Free","Dairy Free","Lacto Ovo Vegetarian","Vegan","Middle Eastern"],"readyInMinutes":40,"likes":5175},{"title":"Butternut Squash and Chicken Mash","id":"Butternut-Squash-and-Chicken-Mash","sourceName":"The Healthy Foodie","image":"images/recipes/Butternut-Squash-and-Chicken-Mash.png","tags":["Paleo","Lunch","Main Course","Main Dish","Dinner","Gluten Free","Dairy Free","Paleolithic","Primal"],"readyInMinutes":45,"likes":4040},{"title":"Cinnamon Pecan Roasted Butternut squas","id":"Cinnamon-Pecan-Roasted-Butternut-squas","sourceName":"Damn Delicious","image":"images/recipes/Cinnamon-Pecan-Roasted-Butternut-squas.jpg","tags":["Vegetarian","Side Dish","Gluten Free","Dairy Free","Lacto Ovo Vegetarian","Fodmap Friendly","Vegan"],"readyInMinutes":40,"likes":2891},{"title":"Butternut Squash and Chickpea Stew with Couscous","id":"Butternut-Squash-and-Chickpea-Stew-with-Couscous","sourceName":"Vegetarian Times","image":"images/recipes/Butternut-Squash-and-Chickpea-Stew-with-Couscous.jpg","tags":["Vegetarian","Lunch","Main Course","Main Dish","Dinner","Dairy Free","Lacto Ovo Vegetarian","Vegan","Fall","Winter"],"readyInMinutes":45,"likes":2109},{"title":"Oven-Roasted Root Vegetables","id":"Oven-Roasted-Root-Vegetables","sourceName":"Foodnetwork","image":"images/recipes/Oven-Roasted-Root-Vegetables.jpeg","tags":["Vegetarian","Side Dish","Gluten Free","Dairy Free","Lacto Ovo Vegetarian","Vegan"],"readyInMinutes":65,"likes":1788},{"title":"My Favorite Autumn Salad","id":"My-Favorite-Autumn-Salad","sourceName":"Nourished Kitchen","image":"images/recipes/My-Favorite-Autumn-Salad.jpg","tags":["Vegetarian","Salad","Gluten Free","Dairy Free","Paleolithic","Lacto Ovo Vegetarian","Primal"],"readyInMinutes":10,"likes":1613},{"title":"kale & apple butternut salad","id":"kale-and-apple-butternut-salad","sourceName":"Love & Lemons","image":"images/recipes/kale-and-apple-butternut-salad.jpg","tags":["Vegetarian","Salad","Gluten Free","Dairy Free","Paleolithic","Lacto Ovo Vegetarian","Primal","Vegan"],"readyInMinutes":45,"likes":1562},{"title":"Herbed Ricotta Butternut Squash Noodles with Walnuts, Chickpeas and Cumin-Roasted Carrots and Cauliflower","id":"Herbed-Ricotta-Butternut-Squash-Noodles-with-Walnuts-Chickpeas-and-Cumin-Roasted-Carrots-and-Cauliflower","sourceName":"Inspiralized","image":"images/recipes/Herbed-Ricotta-Butternut-Squash-Noodles-with-Walnuts-Chickpeas-and-Cumin-Roasted-Carrots-and-Cauliflower.jpg","tags":["Vegetarian","Lunch","Main Course","Main Dish","Dinner","Gluten Free","Lacto Ovo Vegetarian"],"readyInMinutes":45,"likes":1521},{"title":"Beautiful Brussels Sprouts","id":"Beautiful-Brussels-Sprouts","sourceName":"Foodnetwork","image":"images/recipes/Beautiful-Brussels-Sprouts.jpeg","tags":["Vegetarian","Antipasti","Starter","Snack","Appetizer","Antipasto","Hor D'oeuvre","Gluten Free","Dairy Free","Lacto Ovo Vegetarian","Vegan"],"readyInMinutes":50,"likes":1491},{"title":"Roasted Butternut Squash with Garlic, Sage and Pine Nuts","id":"Roasted-Butternut-Squash-with-Garlic-Sage-and-Pine-Nuts","sourceName":"The Shiksa in the Kitchen","image":"images/recipes/Roasted-Butternut-Squash-with-Garlic-Sage-and-Pine-Nuts.jpg","tags":["Vegetarian","Side Dish","Gluten Free","Dairy Free","Paleolithic","Lacto Ovo Vegetarian","Primal","Vegan"],"readyInMinutes":60,"likes":1442},{"title":"Roasted Butternut Squash With Kale And Almond Pecan Parmesan","id":"Roasted-Butternut-Squash-With-Kale-And-Almond-Pecan-Parmesan","sourceName":"Oh She Glows","image":"images/recipes/Roasted-Butternut-Squash-With-Kale-And-Almond-Pecan-Parmesan.jpg","tags":["Vegetarian","Side Dish","Gluten Free","Dairy Free","Paleolithic","Lacto Ovo Vegetarian","Primal","Vegan"],"readyInMinutes":45,"likes":1281},{"title":"Winter Power Salad","id":"Winter-Power-Salad","sourceName":"Laurens Latest","image":"images/recipes/Winter-Power-Salad.png","tags":["Vegetarian","Salad","Lacto Ovo Vegetarian","Winter"],"readyInMinutes":70,"likes":1251},{"title":"Warm Butternut Squash And Chickpea Salad","id":"Warm-Butternut-Squash-And-Chickpea-Salad","sourceName":"Smitten Kitchen","image":"images/recipes/Warm-Butternut-Squash-And-Chickpea-Salad.jpg","tags":["Vegetarian","Side Dish","Gluten Free","Dairy Free","Lacto Ovo Vegetarian","Vegan"],"readyInMinutes":25,"likes":1209},{"title":"Cinnamon Pecan Roasted Butternut Squash","id":"Cinnamon-Pecan-Roasted-Butternut-Squash","sourceName":"Damn Delicious","image":"images/recipes/Cinnamon-Pecan-Roasted-Butternut-Squash.jpg","tags":["Vegetarian","Side Dish","Gluten Free","Dairy Free","Lacto Ovo Vegetarian","Fodmap Friendly","Vegan"],"readyInMinutes":40,"likes":1177},{"title":"Creamy Lentil Stuffed Butternut Squash","id":"Creamy-Lentil-Stuffed-Butternut-Squash","sourceName":"Coconut And Berries","image":"images/recipes/Creamy-Lentil-Stuffed-Butternut-Squash.jpg","tags":["Vegetarian","Side Dish","Gluten Free","Dairy Free","Lacto Ovo Vegetarian","Vegan"],"readyInMinutes":45,"likes":1103}],"name":"butternut squash","page":0,"total":3}
