{"results":[{"title":"Homemade Vegan Calzones with Sun-Dried Tomato & Pesto Spread","id":"Homemade-Vegan-Calzones-with-Sun-Dried-Tomato-and-Pesto-Spread","sourceName":null,"image":"images/recipes/Homemade-Vegan-Calzones-with-Sun-Dried-Tomato-and-Pesto-Spread.jpg","tags":["Vegetarian","Lunch","Main Course","Main Dish","Dinner","Dairy Free","Lacto Ovo Vegetarian","Vegan","Mediterranean","Italian","European"],"readyInMinutes":85,"likes":17272},{"title":"Zucchini Pasta with Garlic Scape Pesto","id":"Zucchini-Pasta-with-Garlic-Scape-Pesto","sourceName":"Queen of Quinoa","image":"images/recipes/Zucchini-Pasta-with-Garlic-Scape-Pesto.jpg","tags":["Vegetarian","Gluten Free","Dairy Free","Paleolithic","Lacto Ovo Vegetarian","Primal","Vegan"],"readyInMinutes":10,"likes":498}],"name":"yeast","page":0,"total":1}
