{"results":[{"title":"Smashed white bean and kale quesadillas with creamy bbq dip","id":"Smashed-white-bean-and-kale-quesadillas-with-creamy-bbq-dip","sourceName":"Running to the Kitchen","image":"images/recipes/Smashed-white-bean-and-kale-quesadillas-with-creamy-bbq-dip.jpg","tags":["Vegetarian","Lunch","Main Course","Main Dish","Dinner","Lacto Ovo Vegetarian","Mexican","Super Bowl"],"readyInMinutes":20,"likes":6521},{"title":"Bok Choy Skillet Supper","id":"Bok-Choy-Skillet-Supper","sourceName":"Vegetarian Times","image":"images/recipes/Bok-Choy-Skillet-Supper.jpg","tags":["Vegetarian","Lunch","Main Course","Main Dish","Dinner","Dairy Free","Lacto Ovo Vegetarian","Vegan"],"readyInMinutes":45,"likes":6451},{"title":"Creamed Spinach Casserole","id":"Creamed-Spinach-Casserole","sourceName":"Eating Well","image":"images/recipes/Creamed-Spinach-Casserole.jpg","tags":["Vegetarian","Side Dish","Lacto Ovo Vegetarian","Fall","Winter"],"readyInMinutes":75,"likes":6371},{"title":"Jalapeño Dijon Grilled Chicken","id":"Jalapeno-Dijon-Grilled-Chicken","sourceName":"Civilized Caveman Cooking","image":"images/recipes/Jalapeno-Dijon-Grilled-Chicken.jpg","tags":["Ketogenic","Lunch","Main Course","Main Dish","Dinner","Gluten Free","Dairy Free","Father's Day","4th Of July","Summer"],"readyInMinutes":30,"likes":6335},{"title":"Slow Cooker Beef Stroganoff","id":"Slow-Cooker-Beef-Stroganoff","sourceName":null,"image":"images/recipes/Slow-Cooker-Beef-Stroganoff.jpg","tags":["Ketogenic","Lunch","Main Course","Main Dish","Dinner","Gluten Free","Eastern European","European"],"readyInMinutes":250,"likes":6253},{"title":"Butternut Squash & Chickpea Coconut Curry (Crock Pot )","id":"Butternut-Squash-and-Chickpea-Coconut-Curry-(Crock-Pot-)","sourceName":"Tasty Yummies","image":"images/recipes/Butternut-Squash-and-Chickpea-Coconut-Curry-(Crock-Pot-).jpg","tags":["Vegetarian","Side Dish","Gluten Free","Dairy Free","Lacto Ovo Vegetarian","Vegan","Indian","Asian"],"readyInMinutes":30,"likes":6244},{"title":"Garlic Roasted Kale","id":"Garlic-Roasted-Kale","sourceName":"Jeanettes Healthy Living","image":"images/recipes/Garlic-Roasted-Kale.jpg","tags":["Vegetarian","Side Dish","Gluten Free","Dairy Free","Paleolithic","Lacto Ovo Vegetarian","Primal","Vegan"],"readyInMinutes":30,"likes":6241},{"title":"Bean Burgers with Spicy Guacamole","id":"Bean-Burgers-with-Spicy-Guacamole","sourceName":"Eating Well","image":"images/recipes/Bean-Burgers-with-Spicy-Guacamole.jpg","tags":["Vegetarian","Side Dish","Dairy Free","Lacto Ovo Vegetarian","Vegan","Mexican"],"readyInMinutes":50,"likes":6213},{"title":"Black Bean and Barley Salad","id":"Black-Bean-and-Barley-Salad","sourceName":"The Lemon Bowl","image":"images/recipes/Black-Bean-and-Barley-Salad.jpg","tags":["Vegetarian","Lunch","Main Course","Main Dish","Dinner","Dairy Free","Lacto Ovo Vegetarian","Vegan"],"readyInMinutes":50,"likes":6162},{"title":"Baked Mustard-Crusted Salmon With Asparagus and Tarragon","id":"Baked-Mustard-Crusted-Salmon-With-Asparagus-and-Tarragon","sourceName":"Epicurious","image":"images/recipes/Baked-Mustard-Crusted-Salmon-With-Asparagus-and-Tarragon.jpg","tags":["Pescetarian","Dairy Free","Pescatarian"],"readyInMinutes":8,"likes":6141},{"title":"Asian Grilled Salmon Pineapple and Rice Lettuce Wraps","id":"Asian-Grilled-Salmon-Pineapple-and-Rice-Lettuce-Wraps","sourceName":"Half Baked Harvest","image":"images/recipes/Asian-Grilled-Salmon-Pineapple-and-Rice-Lettuce-Wraps.jpg","tags":["Pescetarian","Lunch","Main Course","Main Dish","Dinner","Gluten Free","Dairy Free","Pescatarian","Asian","Father's Day","4th Of July","Summer"],"readyInMinutes":60,"likes":6111},{"title":"Curried Chickpeas with Spinach","id":"Curried-Chickpeas-with-Spinach","sourceName":"Budget Bytes","image":"images/recipes/Curried-Chickpeas-with-Spinach.jpg","tags":["Vegetarian","Lunch","Main Course","Main Dish","Dinner","Gluten Free","Dairy Free","Lacto Ovo Vegetarian","Vegan"],"readyInMinutes":25,"likes":6106},{"title":"Strawberry Quinoa and Spinach Caprese Salad","id":"Strawberry-Quinoa-and-Spinach-Caprese-Salad","sourceName":"Closet Cooking","image":"images/recipes/Strawberry-Quinoa-and-Spinach-Caprese-Salad.jpg","tags":["Vegetarian","Side Dish","Gluten Free","Lacto Ovo Vegetarian","Mother's Day"],"readyInMinutes":30,"likes":6097},{"title":"Orzo with Butternut Squash, Spinach & Blue Cheese","id":"Orzo-with-Butternut-Squash-Spinach-and-Blue-Cheese","sourceName":"The Kitchn","image":"images/recipes/Orzo-with-Butternut-Squash-Spinach-and-Blue-Cheese.jpg","tags":["Vegetarian","Side Dish","Lacto Ovo Vegetarian"],"readyInMinutes":45,"likes":6071},{"title":"Easy Vegetarian Quinoa Chili","id":"Easy-Vegetarian-Quinoa-Chili","sourceName":"Food Recipes Hq","image":"images/recipes/Easy-Vegetarian-Quinoa-Chili.png","tags":["Vegetarian","Lunch","Main Course","Main Dish","Dinner","Gluten Free","Dairy Free","Lacto Ovo Vegetarian","Vegan","American","Super Bowl"],"readyInMinutes":45,"likes":6028},{"title":"Breakfast Lasagna","id":"Breakfast-Lasagna","sourceName":"Pale Omg","image":"images/recipes/Breakfast-Lasagna.jpg","tags":["Ketogenic","Morning Meal","Brunch","Breakfast","Gluten Free","Dairy Free","Paleolithic","Primal","Mediterranean","Italian","European"],"readyInMinutes":20,"likes":6015},{"title":"Green Goddess Pasta + Giveaway","id":"Green-Goddess-Pasta-+-Giveaway","sourceName":"Healthy Delicious","image":"images/recipes/Green-Goddess-Pasta-+-Giveaway.jpg","tags":["Vegetarian","Side Dish","Lacto Ovo Vegetarian"],"readyInMinutes":30,"likes":5894},{"title":"Thai Peanut Chicken","id":"Thai-Peanut-Chicken","sourceName":"Budget Bytes","image":"images/recipes/Thai-Peanut-Chicken.jpg","tags":["Ketogenic","Lunch","Main Course","Main Dish","Dinner","Gluten Free","Dairy Free","Thai","Asian"],"readyInMinutes":105,"likes":5890},{"title":"Stuffed Eggplant with Lentils and Millet","id":"Stuffed-Eggplant-with-Lentils-and-Millet","sourceName":"Vegetarian Times","image":"images/recipes/Stuffed-Eggplant-with-Lentils-and-Millet.jpg","tags":["Vegetarian","Side Dish","Gluten Free","Dairy Free","Lacto Ovo Vegetarian","Vegan"],"readyInMinutes":45,"likes":5875},{"title":"Stuffed Portobello Mushrooms with Farro","id":"Stuffed-Portobello-Mushrooms-with-Farro","sourceName":"Vegetarian Times","image":"images/recipes/Stuffed-Portobello-Mushrooms-with-Farro.jpg","tags":["Vegetarian","Side Dish","Lacto Ovo Vegetarian"],"readyInMinutes":45,"likes":5845}],"name":"all","page":8,"total":95}
