{"results":[{"title":"Creamy Heirloom Tomato and Avocado Gazpacho","id":"Creamy-Heirloom-Tomato-and-Avocado-Gazpacho","sourceName":"Blogging Over Thyme","image":"images/recipes/Creamy-Heirloom-Tomato-and-Avocado-Gazpacho.jpg","tags":["Vegetarian","Side Dish","Gluten Free","Dairy Free","Lacto Ovo Vegetarian","Vegan","Summer"],"readyInMinutes":15,"likes":706},{"title":"Israeli Power Salad with Za’atar Roasted Sweet Potatoes","id":"Israeli-Power-Salad-with-Za'atar-Roasted-Sweet-Potatoes","sourceName":"Hummusapien","image":"images/recipes/Israeli-Power-Salad-with-Za'atar-Roasted-Sweet-Potatoes.jpg","tags":["Vegetarian","Salad","Gluten Free","Dairy Free","Lacto Ovo Vegetarian","Vegan"],"readyInMinutes":50,"likes":121}],"name":"persian cucumber","page":0,"total":1}
